opengl_registry/__init__.py
opengl_registry/cli.py
opengl_registry/commands.py
opengl_registry/enums.py
opengl_registry/extensions.py
opengl_registry/features.py
opengl_registry/gltype.py
opengl_registry/reader.py
opengl_registry/registry.py
opengl_registry/writer.py
opengl_registry-0.3.0.dist-info/LICENSE
opengl_registry-0.3.0.dist-info/METADATA
opengl_registry-0.3.0.dist-info/WHEEL
opengl_registry-0.3.0.dist-info/entry_points.txt
opengl_registry-0.3.0.dist-info/top_level.txt
opengl_registry-0.3.0.dist-info/RECORD
