Metadata-Version: 2.1
Name: opengl-registry
Version: 0.3.0
Summary: A simple tool for extracting information from the OpenGL API Registry
Home-page: https://github.com/moderngl/opengl-registry
Author: Einar Forselv
Author-email: eforselv@gmail.com
License: MIT
Project-URL: Documentation, https://opengl-registry.readthedocs.io
Project-URL: OpenGL-Registry, https://github.com/KhronosGroup/OpenGL-Registry
Platform: any
Classifier: License :: OSI Approved :: MIT License
Classifier: Operating System :: OS Independent
Classifier: Topic :: Multimedia :: Graphics
Classifier: Topic :: Multimedia :: Graphics :: 3D Rendering
Classifier: Programming Language :: Python :: 3 :: Only
Requires-Python: >=3.6
Requires-Dist: requests (<3)
